gocardless_events/__init__.py
gocardless_events/py.typed
gocardless_events/models/__init__.py
gocardless_events/models/billing_request.py
gocardless_events/models/creditor.py
gocardless_events/models/export.py
gocardless_events/models/instalment_schedule.py
gocardless_events/models/mandate.py
gocardless_events/models/payer_authorization.py
gocardless_events/models/payment.py
gocardless_events/models/payout.py
gocardless_events/models/refund.py
gocardless_events/models/scheme_identifier.py
gocardless_events/models/subscription.py
gocardless_events-0.1.4.dist-info/METADATA
gocardless_events-0.1.4.dist-info/WHEEL
gocardless_events-0.1.4.dist-info/licenses/LICENSE
gocardless_events-0.1.4.dist-info/RECORD
