Metadata-Version: 2.4
Name: gocardless-events
Version: 0.1.4
Summary: Type-safe Python models for for all GoCardless events using Pydantic
Project-URL: Repository, https://github.com/karoo-ca/gocardless-events.git
Project-URL: Issues, https://github.com/karoo-ca/gocardless-events/issues
License: Copyright 2024 Karoo
License-File: LICENSE
Keywords: gocardless,pydantic
Classifier: Intended Audience :: Developers
Classifier: License :: OSI Approved :: MIT License
Classifier: Operating System :: OS Independent
Classifier: Programming Language :: Python :: 3.13
Classifier: Programming Language :: Python :: Implementation :: CPython
Classifier: Programming Language :: Python :: Implementation :: PyPy
Classifier: Typing :: Typed
Requires-Python: >=3.13
Requires-Dist: pydantic>=2.10.4
